config/__init__.py
config/ddbconfig.py
ddbmodel-0.1.0.dist-info/licenses/LICENSE
tests/__init__.py
tests/test_field.py
tests/test_key.py
tests/test_record.py
tests/test_transaction.py
ddbmodel-0.1.0.dist-info/METADATA
ddbmodel-0.1.0.dist-info/WHEEL
ddbmodel-0.1.0.dist-info/top_level.txt
ddbmodel-0.1.0.dist-info/RECORD
