Metadata-Version: 2.4
Name: ddbmodel
Version: 0.1.0
Summary: A DynamoDB modeling library
Author: Joel Baumert
Author-email: Your Name <your.email@example.com>
License: MIT
Project-URL: Homepage, https://github.com/yourusername/ddbmodel
Project-URL: Repository, https://github.com/yourusername/ddbmodel
Requires-Python: >=3.7
License-File: LICENSE
Requires-Dist: boto3>=1.26.0
Requires-Dist: botocore>=1.29.0
Dynamic: author
Dynamic: license-file
Dynamic: requires-python
